py_ctp/__init__.py
py_ctp/datatype.py
py_ctp/enums.py
py_ctp/quote.py
py_ctp/quote_ctp.py
py_ctp/structs.py
py_ctp/structs_py.py
py_ctp/trade.py
py_ctp/trade_ctp.py
py_ctp/lib64/ctp_quote.dll
py_ctp/lib64/ctp_trade.dll
py_ctp/lib64/libctp_quote.so
py_ctp/lib64/libctp_trade.so
py_ctp/lib64/thostmduserapi_se.dll
py_ctp/lib64/thostmduserapi_se.so
py_ctp/lib64/thosttraderapi_se.dll
py_ctp/lib64/thosttraderapi_se.so
py_ctp-6.7.2.20251003.data/data/README.md
py_ctp-6.7.2.20251003.dist-info/licenses/LICENSE
usr/lib/py_ctp/thostmduserapi_se.so
usr/lib/py_ctp/thosttraderapi_se.so
py_ctp-6.7.2.20251003.dist-info/METADATA
py_ctp-6.7.2.20251003.dist-info/WHEEL
py_ctp-6.7.2.20251003.dist-info/top_level.txt
py_ctp-6.7.2.20251003.dist-info/RECORD
